OpenFF/__init__.py
OpenFF/cli.py
OpenFF/cli2.py
OpenFF/cli3.py
open_freefire-1.3.2.dist-info/licenses/LICENSE
open_freefire-1.3.2.dist-info/METADATA
open_freefire-1.3.2.dist-info/WHEEL
open_freefire-1.3.2.dist-info/entry_points.txt
open_freefire-1.3.2.dist-info/top_level.txt
open_freefire-1.3.2.dist-info/RECORD
