Metadata-Version: 2.4
Name: open-freefire
Version: 1.3.2
Summary: OpenFF: Fetch FF account info and ban status
Home-page: https://pypi.org/project/open-freefire/
Author: Abdul Moeez
Requires-Python: >=3.7
License-File: LICENSE
Requires-Dist: requests
Requires-Dist: argparse
Requires-Dist: colorama
Requires-Dist: datetime
Requires-Dist: lolpython
Requires-Dist: pyfiglet
Dynamic: author
Dynamic: description
Dynamic: description-content-type
Dynamic: home-page
Dynamic: license-file
Dynamic: requires-dist
Dynamic: requires-python
Dynamic: summary
